HDBOBenchmark/__init__.py
HDBOBenchmark/algorithms/__init__.py
HDBOBenchmark/algorithms/add_bo_quasi_nt/__init__.py
HDBOBenchmark/algorithms/add_bo_quasi_nt/addGPLibkky/__init__.py
HDBOBenchmark/algorithms/add_bo_quasi_nt/addGPLibkky/addGPDecompMargLikelihood.py
HDBOBenchmark/algorithms/add_bo_quasi_nt/addGPLibkky/addGPRegression.py
HDBOBenchmark/algorithms/add_bo_quasi_nt/addGPLibkky/augKernel.py
HDBOBenchmark/algorithms/add_bo_quasi_nt/addGPLibkky/combinedKernelNoise.py
HDBOBenchmark/algorithms/add_bo_quasi_nt/addGPLibkky/combinedMeanFunc.py
HDBOBenchmark/algorithms/add_bo_quasi_nt/addGPLibkky/computeCombGPOutput.py
HDBOBenchmark/algorithms/add_bo_quasi_nt/addGPLibkky/computeIndGPOutput.py
HDBOBenchmark/algorithms/add_bo_quasi_nt/addGPLibkky/decompOptPartial.py
HDBOBenchmark/algorithms/add_bo_quasi_nt/addGPLibkky/normRotMargLikelihood.py
HDBOBenchmark/algorithms/add_bo_quasi_nt/BOLibkky/__init__.py
HDBOBenchmark/algorithms/add_bo_quasi_nt/BOLibkky/addGPBO.py
HDBOBenchmark/algorithms/add_bo_quasi_nt/BOLibkky/getAcqUtility.py
HDBOBenchmark/algorithms/add_bo_quasi_nt/BOLibkky/getNextQueryPoint.py
HDBOBenchmark/algorithms/add_bo_quasi_nt/BOLibkky/preprocessDecomposition.py
HDBOBenchmark/algorithms/add_bo_quasi_nt/main.py
HDBOBenchmark/algorithms/add_bo_quasi_nt/my_generation/__init__.py
HDBOBenchmark/algorithms/add_bo_quasi_nt/my_generation/gen.py
HDBOBenchmark/algorithms/add_bo_quasi_nt/my_optim/__init__.py
HDBOBenchmark/algorithms/add_bo_quasi_nt/my_optim/initializers.py
HDBOBenchmark/algorithms/add_bo_quasi_nt/my_optim/optimize.py
HDBOBenchmark/algorithms/add_bo_quasi_nt/my_optim/parameter_constraints.py
HDBOBenchmark/algorithms/add_bo_quasi_nt/my_optim/utils.py
HDBOBenchmark/algorithms/add_bo_quasi_nt/my_utils/__init__.py
HDBOBenchmark/algorithms/add_bo_quasi_nt/my_utils/sampling_scipy.py
HDBOBenchmark/algorithms/add_bo_quasi_nt/my_utils/sampling_torch.py
HDBOBenchmark/algorithms/add_bo_quasi_nt/utils/__init__.py
hdbo_b-0.2.0.dist-info/LICENSE
hdbo_b-0.2.0.dist-info/METADATA
hdbo_b-0.2.0.dist-info/WHEEL
hdbo_b-0.2.0.dist-info/RECORD
