Metadata-Version: 2.3
Name: hdbo-b
Version: 0.2.0
Summary: High-Dimentional Bayesian Benchmark (HDBO-B)
License: MIT
Keywords: hdbo,benchmark
Author: yiyuiii
Author-email: yiyuiii@foxmail.com
Requires-Python: >=3.8,<4.0
Classifier: License :: OSI Approved :: MIT License
Classifier: Programming Language :: Python :: 3
Classifier: Programming Language :: Python :: 3.8
Classifier: Programming Language :: Python :: 3.9
Classifier: Programming Language :: Python :: 3.10
Classifier: Programming Language :: Python :: 3.11
Classifier: Programming Language :: Python :: 3.12
Classifier: Programming Language :: Python :: 3.13
Provides-Extra: alebo
Provides-Extra: hebo
Provides-Extra: hpobench
Provides-Extra: mip
Provides-Extra: pde
Requires-Dist: botorch (>=0.8.5,<0.9.0)
Requires-Dist: matplotlib (>=3.5.2,<4.0.0)
Requires-Dist: numpy (>=1.21.5,<2.0.0)
Requires-Dist: pillow (>=9.2.0,<10.0.0)
Requires-Dist: requests (>=2.31.0,<3.0.0)
Requires-Dist: scipy (>=1.9.1,<2.0.0)
Requires-Dist: seaborn (>=0.13.1,<0.14.0)
Project-URL: Documentation, https://github.com/yiyuiii/hdbo-b#readme
Project-URL: Homepage, https://github.com/yiyuiii/hdbo-b
Project-URL: Repository, https://github.com/yiyuiii/hdbo-b
